{
  "name": "AsTeRICS Grid default",
  "author": "AsTeRICS Foundation / UAS Technikum Wien",
  "website": "https://www.asterics-foundation.org/1270-2/",
  "languages": ["ar", "bn", "bg", "zh", "en", "fr", "de", "he", "hi", "id", "it", "ja", "pl", "pt", "ro", "ru", "sr", "es", "tr", "uk", "ur"],
  "description": {
    "en": "Demo configuration containing examples for basic communication, a YouTube player, webradio player, different keyboards and environmental control.",
    "de": "Demo Konfiguration für einfache Kommunikation, einen YouTube-Player, Webradio-Player, verschiedene Keyboard-Layouts und Umgebungssteuerung."
  },
  "standardFor": ["de"],
  "wordPrediction": true,
  "tags": ["BASIC_COMMUNICATION", "4x5"],
  "selfContained": true
}